HoloOps/HoloOps.py
HoloOps/__init__.py
HoloOps/HOUtils/HOUtils.py
HoloOps/HOUtils/__init__.py
holoops-0.1.1.dist-info/METADATA
holoops-0.1.1.dist-info/WHEEL
holoops-0.1.1.dist-info/top_level.txt
holoops-0.1.1.dist-info/RECORD
