Metadata-Version: 2.4
Name: HoloOps
Version: 0.1.1
Summary: Unified, production-ready file and directory management for modern Python applications.
Author: Tristan McBride Sr.
Author-email: "Tristan McBride Sr." <142635792+TristanMcBrideSr@users.noreply.github.com>
Maintainer-email: "Tristan McBride Sr." <142635792+TristanMcBrideSr@users.noreply.github.com>
License-Expression: Apache-2.0
Project-URL: Homepage, https://github.com/TristanMcBrideSr
Keywords: Python,File Management,Directory Management,Project Root Detection,Cloud Storage,Automation,AI Tools,Productivity
Classifier: Programming Language :: Python :: 3
Classifier: Operating System :: OS Independent
Classifier: Intended Audience :: Developers
Requires-Python: >=3.10
Dynamic: author
